garminconnect-0.2.34.dist-info/METADATA
garminconnect-0.2.34.dist-info/WHEEL
garminconnect-0.2.34.dist-info/entry_points.txt
garminconnect-0.2.34.dist-info/licenses/LICENSE
garminconnect/__init__.py
garminconnect/fit.py
garminconnect-0.2.34.dist-info/RECORD
